fqxtest/Aggregates.py
fqxtest/Aggregates.pyi
fqxtest/DateCorr.py
fqxtest/DateCorr.pyi
fqxtest/Fetch_Trading_Data.py
fqxtest/Fetch_Trading_Data.pyi
fqxtest/FiinIndicator.py
fqxtest/FiinIndicator.pyi
fqxtest/FiinQuant.py
fqxtest/FiinQuant.pyi
fqxtest/GetDataPoint.py
fqxtest/GetDataPoint.pyi
fqxtest/RealTimeData.py
fqxtest/RealTimeData.pyi
fqxtest/Rebalance.py
fqxtest/Rebalance.pyi
fqxtest/SimilarChart.py
fqxtest/SimilarChart.pyi
fqxtest/Trading_Data_Stream.py
fqxtest/Trading_Data_Stream.pyi
fqxtest/__init__.py
fqxtest/__init__.pyi
fqxtest-0.1.9.dist-info/METADATA
fqxtest-0.1.9.dist-info/WHEEL
fqxtest-0.1.9.dist-info/top_level.txt
fqxtest-0.1.9.dist-info/RECORD
